dinjectorr/__init__.py
dinjectorr/inject.py
dinjectorr/injector.py
tests/__init__.py
tests/test_dinjectorr.py
dinjectorr-0.1.8.dist-info/LICENSE
dinjectorr-0.1.8.dist-info/METADATA
dinjectorr-0.1.8.dist-info/WHEEL
dinjectorr-0.1.8.dist-info/top_level.txt
dinjectorr-0.1.8.dist-info/RECORD
